pytest_progress/__init__.py
pytest_progress-1.4.0.dist-info/licenses/LICENSE
pytest_progress-1.4.0.dist-info/METADATA
pytest_progress-1.4.0.dist-info/WHEEL
pytest_progress-1.4.0.dist-info/entry_points.txt
pytest_progress-1.4.0.dist-info/top_level.txt
pytest_progress-1.4.0.dist-info/RECORD
