Metadata-Version: 2.4
Name: pytest-progress
Version: 1.4.0
Summary: pytest plugin for instant test progress status
Home-page: https://github.com/ssrikanta/pytest-progress
Author: santosh
Author-email: Santosh Srikanta <santosh.srikanta@gmail.com>
License: MIT License
Project-URL: Homepage, https://github.com/ssrikanta/pytest-progress
Project-URL: Repository, https://github.com/ssrikanta/pytest-progress
Project-URL: Issues, https://github.com/ssrikanta/pytest-progress/issues
Keywords: py.test,pytest,report
Classifier: Development Status :: 5 - Production/Stable
Classifier: Framework :: Pytest
Classifier: Intended Audience :: Developers
Classifier: License :: OSI Approved :: MIT License
Classifier: Operating System :: POSIX
Classifier: Operating System :: Microsoft :: Windows
Classifier: Operating System :: MacOS :: MacOS X
Classifier: Topic :: Software Development :: Testing
Classifier: Topic :: Software Development :: Quality Assurance
Classifier: Topic :: Software Development :: Libraries
Classifier: Topic :: Utilities
Classifier: Programming Language :: Python :: 3.8
Classifier: Programming Language :: Python :: 3.9
Classifier: Programming Language :: Python :: 3.10
Classifier: Programming Language :: Python :: 3.11
Classifier: Programming Language :: Python :: 3.12
Classifier: Programming Language :: Python :: 3.13
Requires-Python: >=3.8
License-File: LICENSE
Requires-Dist: pytest>=6.0
Dynamic: author
Dynamic: home-page
Dynamic: license-file
Dynamic: requires-python
